odoo/addons/product_analytic_purchase/README.rst
odoo/addons/product_analytic_purchase/__init__.py
odoo/addons/product_analytic_purchase/__manifest__.py
odoo/addons/product_analytic_purchase/i18n/ca.po
odoo/addons/product_analytic_purchase/i18n/cs_CZ.po
odoo/addons/product_analytic_purchase/i18n/es.po
odoo/addons/product_analytic_purchase/i18n/fr.po
odoo/addons/product_analytic_purchase/i18n/hr.po
odoo/addons/product_analytic_purchase/i18n/product_analytic_purchase.pot
odoo/addons/product_analytic_purchase/models/__init__.py
odoo/addons/product_analytic_purchase/models/purchase_order_line.py
odoo/addons/product_analytic_purchase/static/description/icon.png
odoo/addons/product_analytic_purchase/tests/__init__.py
odoo/addons/product_analytic_purchase/tests/test_purchase.py
odoo14_addon_product_analytic_purchase-14.0.1.0.1.dist-info/METADATA
odoo14_addon_product_analytic_purchase-14.0.1.0.1.dist-info/WHEEL
odoo14_addon_product_analytic_purchase-14.0.1.0.1.dist-info/top_level.txt
odoo14_addon_product_analytic_purchase-14.0.1.0.1.dist-info/RECORD
